[
  {
    "id": "751d1a44-bd35-4545-9743-c11af2180018",
    "filename": "安徽航瑞航空动力装备有限公司-非道路手册2025版.pdf",
    "file_type": "pdf",
    "file_size": 8646553,
    "file_path": "uploads/751d1a44-bd35-4545-9743-c11af2180018/安徽航瑞航空动力装备有限公司-非道路手册2025版.pdf",
    "title": "安徽航瑞航空动力装备有限公司-非道路手册2025版",
    "description": null,
    "status": "ready",
    "chunk_count": 53,
    "tags": [],
    "uploaded_at": "2026-06-02T15:40:10.218340",
    "updated_at": "2026-06-02T15:44:26.160505"
  },
  {
    "id": "fe63a51d-c418-40fa-9084-eb8852dd0590",
    "filename": "产品购销合同(75).pdf",
    "file_type": "pdf",
    "file_size": 1033401,
    "file_path": "uploads/fe63a51d-c418-40fa-9084-eb8852dd0590/产品购销合同(75).pdf",
    "title": "产品购销合同(75)",
    "description": null,
    "status": "ready",
    "chunk_count": 5,
    "tags": [],
    "uploaded_at": "2026-06-02T15:40:19.767184",
    "updated_at": "2026-06-02T15:40:37.446992"
  },
  {
    "id": "758d2319-9822-4202-83e6-b08d9242753b",
    "filename": "Tattu Brand Brochure - Double Page - 2026.pdf",
    "file_type": "pdf",
    "file_size": 15069129,
    "file_path": "uploads/758d2319-9822-4202-83e6-b08d9242753b/Tattu Brand Brochure - Double Page - 2026.pdf",
    "title": "Tattu Brand Brochure - Double Page - 2026",
    "description": null,
    "status": "ready",
    "chunk_count": 38,
    "tags": [],
    "uploaded_at": "2026-06-02T16:06:24.780675",
    "updated_at": "2026-06-02T16:11:30.886068"
  },
  {
    "id": "f70057ae-b769-4c21-a011-b0242c709ff3",
    "filename": "Grepow charger catalog.pdf",
    "file_type": "pdf",
    "file_size": 1970987,
    "file_path": "uploads/f70057ae-b769-4c21-a011-b0242c709ff3/Grepow charger catalog.pdf",
    "title": "Grepow charger catalog",
    "description": null,
    "status": "ready",
    "chunk_count": 76,
    "tags": [],
    "uploaded_at": "2026-06-02T16:06:34.635684",
    "updated_at": "2026-06-02T16:09:26.742220"
  },
  {
    "id": "f4f56c71-c6ee-4343-b910-169b19ac39dc",
    "filename": "凡双低空安全管理解决方案2026.pdf",
    "file_type": "pdf",
    "file_size": 3697066,
    "file_path": "uploads/f4f56c71-c6ee-4343-b910-169b19ac39dc/凡双低空安全管理解决方案2026.pdf",
    "title": "凡双低空安全管理解决方案2026",
    "description": null,
    "status": "ready",
    "chunk_count": 58,
    "tags": [],
    "uploaded_at": "2026-06-02T16:07:11.739992",
    "updated_at": "2026-06-02T16:11:42.684759"
  },
  {
    "id": "7ff901ee-958c-48cc-90ee-3362ddb01b01",
    "filename": "catalog.pdf",
    "file_type": "pdf",
    "file_size": 24275524,
    "file_path": "uploads/7ff901ee-958c-48cc-90ee-3362ddb01b01/catalog.pdf",
    "title": "catalog",
    "description": null,
    "status": "ready",
    "chunk_count": 105,
    "tags": [],
    "uploaded_at": "2026-06-02T16:21:57.020876",
    "updated_at": "2026-06-02T16:31:30.241447"
  },
  {
    "id": "5a4d3a88-b336-4f89-98db-b2951c3fcb6d",
    "filename": "Anti-UAV System.pdf",
    "file_type": "pdf",
    "file_size": 17535398,
    "file_path": "uploads/5a4d3a88-b336-4f89-98db-b2951c3fcb6d/Anti-UAV System.pdf",
    "title": "Anti-UAV System",
    "description": null,
    "status": "ready",
    "chunk_count": 19,
    "tags": [],
    "uploaded_at": "2026-06-02T16:22:10.648662",
    "updated_at": "2026-06-02T16:24:05.563213"
  },
  {
    "id": "46f7356e-cc9e-4003-98a5-a35be3ea916d",
    "filename": "Q系列  CHS-1.6.5-20260507.pdf",
    "file_type": "pdf",
    "file_size": 15677905,
    "file_path": "uploads/46f7356e-cc9e-4003-98a5-a35be3ea916d/Q系列  CHS-1.6.5-20260507.pdf",
    "title": "Q系列  CHS-1.6.5-20260507",
    "description": null,
    "status": "ready",
    "chunk_count": 105,
    "tags": [],
    "uploaded_at": "2026-06-02T16:27:43.966954",
    "updated_at": "2026-06-02T17:03:26.049072"
  },
  {
    "id": "3c552d0c-5c9c-45b6-94fe-2cc0b97d03c5",
    "filename": "深圳市建弘实业有限公司整机目录.pdf",
    "file_type": "pdf",
    "file_size": 17930600,
    "file_path": "uploads/3c552d0c-5c9c-45b6-94fe-2cc0b97d03c5/深圳市建弘实业有限公司整机目录.pdf",
    "title": "深圳市建弘实业有限公司整机目录",
    "description": null,
    "status": "ready",
    "chunk_count": 28,
    "tags": [],
    "uploaded_at": "2026-06-02T16:28:24.821478",
    "updated_at": "2026-06-02T17:14:13.327120"
  },
  {
    "id": "6d4e0c1f-460f-45ae-b72f-2ceace7c7d50",
    "filename": "A10型低空监视雷达规格书.docx",
    "file_type": "docx",
    "file_size": 6865791,
    "file_path": "uploads/6d4e0c1f-460f-45ae-b72f-2ceace7c7d50/A10型低空监视雷达规格书.docx",
    "title": "A10型低空监视雷达规格书",
    "description": null,
    "status": "ready",
    "chunk_count": 4,
    "tags": [],
    "uploaded_at": "2026-06-02T16:28:30.486899",
    "updated_at": "2026-06-02T16:28:33.476524"
  }
]